elections_canada_mcp/__init__.py
elections_canada_mcp/constants.py
elections_canada_mcp/server.py
elections_canada_mcp/utils.py
elections_canada_mcp/datafiles/2021_riding_vote_redistributed_ElectionsCanada.json
elections_canada_mcp_server-0.1.3.dist-info/licenses/LICENSE
elections_canada_mcp_server-0.1.3.dist-info/METADATA
elections_canada_mcp_server-0.1.3.dist-info/WHEEL
elections_canada_mcp_server-0.1.3.dist-info/entry_points.txt
elections_canada_mcp_server-0.1.3.dist-info/top_level.txt
elections_canada_mcp_server-0.1.3.dist-info/RECORD
