Metadata-Version: 2.4
Name: elections_canada_mcp_server
Version: 0.1.3
Summary: MCP server for Elections Canada data
Author: Rohan Sampath
License-Expression: MIT
Project-URL: Homepage, https://github.com/ThreeFortyThree-Canada/elections-canada-mcp-server
Classifier: Development Status :: 4 - Beta
Classifier: Intended Audience :: Developers
Classifier: Intended Audience :: Science/Research
Classifier: Operating System :: OS Independent
Classifier: Programming Language :: Python :: 3
Classifier: Programming Language :: Python :: 3.12
Classifier: Topic :: Scientific/Engineering :: Information Analysis
Classifier: Topic :: Software Development :: Libraries :: Python Modules
Requires-Python: >=3.12
License-File: LICENSE
Requires-Dist: mcp[cli]>=1.6.0
Requires-Dist: fastapi==0.110.0
Requires-Dist: uvicorn>=0.21.1
Requires-Dist: pydantic>=1.10.7
Requires-Dist: python-dotenv>=1.0.0
Requires-Dist: pandas>=2.0.0
Provides-Extra: dev
Requires-Dist: black; extra == "dev"
Requires-Dist: flake8; extra == "dev"
Requires-Dist: pytest; extra == "dev"
Requires-Dist: mypy; extra == "dev"
Dynamic: license-file
